pepsipy/__init__.py
pepsipy/__main__.py
pepsipy/api.py
pepsipy/constants.py
pepsipy/features.py
pepsipy/plots.py
pepsipy/utils.py
pepsipy-1.1.0.dist-info/licenses/LICENSE
pepsipy-1.1.0.dist-info/METADATA
pepsipy-1.1.0.dist-info/WHEEL
pepsipy-1.1.0.dist-info/entry_points.txt
pepsipy-1.1.0.dist-info/top_level.txt
pepsipy-1.1.0.dist-info/RECORD
