Metadata-Version: 2.4
Name: pepsipy
Version: 1.1.0
Summary: A library to calculate peptide features.
Author-email: Ronja Krueger <ronja.krueger@student.hpi.de>
License-Expression: MIT
Project-URL: Repository, https://github.com/ronjakrg/pepsipy
Project-URL: Issues, https://github.com/ronjakrg/pepsipy/issues
Keywords: bioinformatics,peptides
Classifier: Programming Language :: Python :: 3
Classifier: Operating System :: OS Independent
Requires-Python: >=3.11
License-File: LICENSE
Requires-Dist: numpy==2.3.0
Requires-Dist: pandas==2.3.0
Requires-Dist: plotly==6.1.2
Requires-Dist: kaleido==0.2.1
Requires-Dist: scikit-learn==1.7.0
Requires-Dist: modlamp==4.3.2
Dynamic: license-file
